README.md
setup.cfg
setup.py
exacto/__init__.py
exacto/rules.py
exacto/tools.py
exacto.egg-info/PKG-INFO
exacto.egg-info/SOURCES.txt
exacto.egg-info/dependency_links.txt
exacto.egg-info/requires.txt
exacto.egg-info/top_level.txt
exacto.egg-info/zip-safe