Metadata-Version: 2.1
Name: exacto
Version: 0.2.2
Summary: Python tools for splitting strings.
Home-page: http://github.com/arthexis/exacto
Author: Rafael Guillén
Author-email: arthexis@gmail.com
License: MIT
Download-URL: https://github.com/arthexis/exacto/archive/v0.2.2.tar.gz
Keywords: UTILS,SPLIT,STRING
Platform: UNKNOWN
Classifier: Development Status :: 3 - Alpha
Classifier: Intended Audience :: Developers
Classifier: Topic :: Software Development :: Libraries
Classifier: Topic :: Text Processing
Classifier: Topic :: Utilities
Classifier: License :: OSI Approved :: MIT License
Classifier: Programming Language :: Python :: 3
Classifier: Programming Language :: Python :: 3.6
Classifier: Programming Language :: Python :: 3.7
Provides-Extra: dev
